MANIFEST.in
README.rst
setup.py
jawiki/__init__.py
jawiki/jawiki.py
jawiki.egg-info/PKG-INFO
jawiki.egg-info/SOURCES.txt
jawiki.egg-info/dependency_links.txt
jawiki.egg-info/not-zip-safe
jawiki.egg-info/requires.txt
jawiki.egg-info/top_level.txt