Metadata-Version: 1.0
Name: jawiki
Version: 1.4.0.2
Summary: A Pythonic wrapper for the Japanese Wikipedia API
Home-page: http://github.com/tex2e/jawiki
Author: tex2e
Author-email: mnfeconicu41@gmail.com
License: MIT
Platform: UNKNOWN
